README.rst
colorize.py
setup.py
colorize.py.egg-info/PKG-INFO
colorize.py.egg-info/SOURCES.txt
colorize.py.egg-info/dependency_links.txt
colorize.py.egg-info/requires.txt
colorize.py.egg-info/top_level.txt