Metadata-Version: 1.2
Name: colorize.py
Version: 0.9.1
Summary: Add colors to plain text lines matching either a Python string or regular expression
Home-page: https://github.com/hq6/Colorize
Author: Henry Qin
Author-email: root@hq6.me
License: MIT
Platform: Any Platform supporting ANSI escape codes
Requires-Python: >=2.7
